pubkeeper/__init__.py
pubkeeper/client.py
pubkeeper/brew/__init__.py
pubkeeper/brew/base.py
pubkeeper/brew/brew_state.py
pubkeeper/brewer/__init__.py
pubkeeper/brewer/brewer.py
pubkeeper/patron/__init__.py
pubkeeper/patron/patron.py
pubkeeper/protocol/__init__.py
pubkeeper/protocol/v1/__init__.py
pubkeeper/protocol/v1/handler.py
pubkeeper/protocol/v1/brewer/__init__.py
pubkeeper/protocol/v1/brewer/brewer.py
pubkeeper/protocol/v1/patron/__init__.py
pubkeeper/protocol/v1/patron/patron.py
pubkeeper/protocol/v1/segment/__init__.py
pubkeeper/protocol/v1/segment/info.py
pubkeeper/protocol/v1/segment/manager.py
pubkeeper/protocol/v1/segment/translator.py
pubkeeper/topic/__init__.py
pubkeeper/topic/topic.py
pubkeeper/utils/__init__.py
pubkeeper/utils/crypto.py
pubkeeper/utils/exceptions.py
pubkeeper/utils/function_table.py
pubkeeper/utils/host.py
pubkeeper/utils/interface.py
pubkeeper/utils/logging.py
pubkeeper/utils/port_manager.py
pubkeeper/utils/websocket.py
pubkeeper.client-1.1.4.dist-info/DESCRIPTION.rst
pubkeeper.client-1.1.4.dist-info/METADATA
pubkeeper.client-1.1.4.dist-info/RECORD
pubkeeper.client-1.1.4.dist-info/WHEEL
pubkeeper.client-1.1.4.dist-info/metadata.json
pubkeeper.client-1.1.4.dist-info/top_level.txt
