Metadata-Version: 2.0
Name: pubkeeper.client
Version: 1.1.4
Summary: Brew, Fill, Consume
Home-page: http://github.com/pubkeeper/python-client
Author: n.io
Author-email: info@n.io
License: UNKNOWN
Keywords: pubkeeper,client-python
Platform: UNKNOWN
Classifier: License :: Other/Proprietary License
Classifier: Programming Language :: Python :: 3
Classifier: Programming Language :: Python :: 3.5
Requires-Dist: pubkeeper.protocol.v1 (~=1.1)
Requires-Dist: pycryptodome (~=3.4)
Requires-Dist: tornado (~=4.5)
